RubyOnRailsZhinan/README.md
RubyOnRailsZhinan/__init__.py
RubyOnRailsZhinan/__main__.py
RubyOnRailsZhinan/file.epub
RubyOnRailsZhinan/index.html
RubyOnRailsZhinan/css/__init__.py
RubyOnRailsZhinan/css/annotations.css
RubyOnRailsZhinan/css/main.css
RubyOnRailsZhinan/css/normalize.css
RubyOnRailsZhinan/css/popup.css
RubyOnRailsZhinan/font/__init__.py
RubyOnRailsZhinan/font/fontello.eot
RubyOnRailsZhinan/font/fontello.svg
RubyOnRailsZhinan/font/fontello.ttf
RubyOnRailsZhinan/font/fontello.woff
RubyOnRailsZhinan/img/__init__.py
RubyOnRailsZhinan/img/annotator-glyph-sprite.png
RubyOnRailsZhinan/img/annotator-icon-sprite.png
RubyOnRailsZhinan/img/apple-touch-icon.png
RubyOnRailsZhinan/img/cancelfullscreen.png
RubyOnRailsZhinan/img/close.png
RubyOnRailsZhinan/img/fullscreen.png
RubyOnRailsZhinan/img/loader.gif
RubyOnRailsZhinan/img/menu-icon.png
RubyOnRailsZhinan/img/save.png
RubyOnRailsZhinan/img/saved.png
RubyOnRailsZhinan/img/settings-s.png
RubyOnRailsZhinan/img/settings.png
RubyOnRailsZhinan/img/star.png
RubyOnRailsZhinan/js/__init__.py
RubyOnRailsZhinan/js/epub.js
RubyOnRailsZhinan/js/epub.min.js
RubyOnRailsZhinan/js/epub.min.map
RubyOnRailsZhinan/js/hooks.min.js
RubyOnRailsZhinan/js/hooks.min.map
RubyOnRailsZhinan/js/reader.js
RubyOnRailsZhinan/js/reader.js.map
RubyOnRailsZhinan/js/reader.min.js
RubyOnRailsZhinan/js/reader.min.map
RubyOnRailsZhinan/js/hooks/__init__.py
RubyOnRailsZhinan/js/hooks/extensions/__init__.py
RubyOnRailsZhinan/js/hooks/extensions/highlight.js
RubyOnRailsZhinan/js/libs/__init__.py
RubyOnRailsZhinan/js/libs/jquery.min.js
RubyOnRailsZhinan/js/libs/localforage.min.js
RubyOnRailsZhinan/js/libs/screenfull.js
RubyOnRailsZhinan/js/libs/screenfull.min.js
RubyOnRailsZhinan/js/libs/zip.min.js
RubyOnRailsZhinan/js/plugins/__init__.py
RubyOnRailsZhinan/js/plugins/hypothesis.js
RubyOnRailsZhinan/js/plugins/search.js
ruby_on_rails_zhinan-2024.3.2.0.dist-info/METADATA
ruby_on_rails_zhinan-2024.3.2.0.dist-info/WHEEL
ruby_on_rails_zhinan-2024.3.2.0.dist-info/entry_points.txt
ruby_on_rails_zhinan-2024.3.2.0.dist-info/top_level.txt
ruby_on_rails_zhinan-2024.3.2.0.dist-info/RECORD
